aeryl_sdk/__init__.py
aeryl_sdk/aeryl_model.py
aeryl_sdk/chaos_classifier.py
aeryl_sdk/core.py
aeryl_sdk/dataset.py
aeryl_sdk/metrics.py
aeryl_sdk/model_wrapper.py
aeryl_sdk-0.1.2.dist-info/licenses/LICENSE
aeryl_sdk-0.1.2.dist-info/METADATA
aeryl_sdk-0.1.2.dist-info/WHEEL
aeryl_sdk-0.1.2.dist-info/top_level.txt
aeryl_sdk-0.1.2.dist-info/RECORD
