Metadata-Version: 2.4
Name: aeryl_sdk
Version: 0.1.2
Summary: Aeryl SDK for chaos testing and error detection
Home-page: https://github.com/aeryl-ai/aeryl_sdk
Author: Aeryl AI
Author-email: Aeryl AI <info@aeryl.ai>
License: MIT
Project-URL: Homepage, https://github.com/aeryl-ai/aeryl_sdk
Project-URL: Repository, https://github.com/aeryl-ai/aeryl_sdk.git
Project-URL: Documentation, https://github.com/aeryl-ai/aeryl_sdk#readme
Classifier: Development Status :: 4 - Beta
Classifier: Intended Audience :: Developers
Classifier: License :: OSI Approved :: MIT License
Classifier: Programming Language :: Python :: 3
Classifier: Programming Language :: Python :: 3.8
Classifier: Programming Language :: Python :: 3.9
Classifier: Programming Language :: Python :: 3.10
Classifier: Programming Language :: Python :: 3.11
Requires-Python: >=3.8
License-File: LICENSE
Requires-Dist: numpy>=1.24.0
Requires-Dist: pandas>=2.0.0
Requires-Dist: polars>=0.20.0
Requires-Dist: scikit-learn>=1.3.0
Requires-Dist: torch>=2.0.0
Requires-Dist: tqdm>=4.65.0
Requires-Dist: sentence-transformers>=2.2.0
Requires-Dist: xgboost>=1.7.0
Dynamic: author
Dynamic: home-page
Dynamic: license-file
Dynamic: requires-python
